auto_feat_ml/__init__.py
auto_feat_ml/data_models/__init_.py
auto_feat_ml/data_models/feature_model.py
auto_feat_ml/feature_selection.py
auto_feat_ml-0.0.2.dist-info/METADATA
auto_feat_ml-0.0.2.dist-info/WHEEL
auto_feat_ml-0.0.2.dist-info/RECORD
