Metadata-Version: 2.1
Name: auto-feat-ml
Version: 0.0.2
Summary: Automatic Feature Selection with Machine Learning for Machine Learning Classification and Regression models
Author: Yannick Flores
Author-email: yannick.flores1992@gmail.com
Requires-Python: >=3.11,<4.0
Classifier: Programming Language :: Python :: 3
Classifier: Programming Language :: Python :: 3.11
Classifier: Programming Language :: Python :: 3.12
Requires-Dist: boto3 (==1.34.*)
Requires-Dist: boto3-stubs[s3] (==1.34.*)
Requires-Dist: pydantic (>=2.6.1,<3.0.0)
Requires-Dist: pymongo (==4.6.*)
